{"basePath":"","rootUrl":"https://games.googleapis.com/","resources":{"accesstokens":{"methods":{"generatePlayGroupingApiToken":{"flatPath":"games/v1/accesstokens/generatePlayGroupingApiToken","httpMethod":"POST","id":"games.accesstokens.generatePlayGroupingApiToken","parameterOrder":[],"parameters":{"packageName":{"location":"query","type":"string"},"persona":{"location":"query","type":"string"}},"path":"games/v1/accesstokens/generatePlayGroupingApiToken","response":{"$ref":"GeneratePlayGroupingApiTokenResponse"},"scopes":["https://www.googleapis.com/auth/games"]},"generateRecallPlayGroupingApiToken":{"flatPath":"games/v1/accesstokens/generateRecallPlayGroupingApiToken","httpMethod":"POST","id":"games.accesstokens.generateRecallPlayGroupingApiToken","parameterOrder":[],"parameters":{"packageName":{"location":"query","type":"string"},"persona":{"location":"query","type":"string"},"recallSessionId":{"location":"query","type":"string"}},"path":"games/v1/accesstokens/generateRecallPlayGroupingApiToken","response":{"$ref":"GenerateRecallPlayGroupingApiTokenResponse"},"scopes":["https://www.googleapis.com/auth/androidpublisher"]}}},"achievementDefinitions":{"methods":{"list":{"flatPath":"games/v1/achievements","httpMethod":"GET","id":"games.achievementDefinitions.list","parameterOrder":[],"parameters":{"language":{"location":"query","type":"string"},"maxResults":{"format":"int32","location":"query","type":"integer"},"pageToken":{"location":"query","type":"string"}},"path":"games/v1/achievements","response":{"$ref":"AchievementDefinitionsListResponse"},"scopes":["https://www.googleapis.com/auth/games"]}}},"achievements":{"methods":{"increment":{"flatPath":"games/v1/achievements/{achievementId}/increment","httpMethod":"POST","id":"games.achievements.increment","parameterOrder":["achievementId","stepsToIncrement"],"parameters":{"achievementId":{"location":"path","required":true,"type":"string"},"requestId":{"format":"int64","location":"query","type":"string"},"stepsToIncrement":{"format":"int32","location":"query","required":true,"type":"integer"}},"path":"games/v1/achievements/{achievementId}/increment","response":{"$ref":"AchievementIncrementResponse"},"scopes":["https://www.googleapis.com/auth/games"]},"list":{"flatPath":"games/v1/players/{playerId}/achievements","httpMethod":"GET","id":"games.achievements.list","parameterOrder":["playerId"],"parameters":{"language":{"location":"query","type":"string"},"maxResults":{"format":"int32","location":"query","type":"integer"},"pageToken":{"location":"query","type":"string"},"playerId":{"location":"path","required":true,"type":"string"},"state":{"enum":["ALL","HIDDEN","REVEALED","UNLOCKED"],"enumDescriptions":["List all achievements. This is the default.","List only hidden achievements.","List only revealed achievements.","List only unlocked achievements."],"location":"query","type":"string"}},"path":"games/v1/players/{playerId}/achievements","response":{"$ref":"PlayerAchievementListResponse"},"scopes":["https://www.googleapis.com/auth/games"]},"reveal":{"flatPath":"games/v1/achievements/{achievementId}/reveal","httpMethod":"POST","id":"games.achievements.reveal","parameterOrder":["achievementId"],"parameters":{"achievementId":{"location":"path","required":true,"type":"string"}},"path":"games/v1/achievements/{achievementId}/reveal","response":{"$ref":"AchievementRevealResponse"},"scopes":["https://www.googleapis.com/auth/games"]},"setStepsAtLeast":{"flatPath":"games/v1/achievements/{achievementId}/setStepsAtLeast","httpMethod":"POST","id":"games.achievements.setStepsAtLeast","parameterOrder":["achievementId","steps"],"parameters":{"achievementId":{"location":"path","required":true,"type":"string"},"steps":{"format":"int32","location":"query","required":true,"type":"integer"}},"path":"games/v1/achievements/{achievementId}/setStepsAtLeast","response":{"$ref":"AchievementSetStepsAtLeastResponse"},"scopes":["https://www.googleapis.com/auth/games"]},"unlock":{"flatPath":"games/v1/achievements/{achievementId}/unlock","httpMethod":"POST","id":"games.achievements.unlock","parameterOrder":["achievementId"],"parameters":{"achievementId":{"location":"path","required":true,"type":"string"}},"path":"games/v1/achievements/{achievementId}/unlock","response":{"$ref":"AchievementUnlockResponse"},"scopes":["https://www.googleapis.com/auth/games"]},"updateMultiple":{"flatPath":"games/v1/achievements/updateMultiple","httpMethod":"POST","id":"games.achievements.updateMultiple","parameterOrder":[],"parameters":{},"path":"games/v1/achievements/updateMultiple","request":{"$ref":"AchievementUpdateMultipleRequest"},"response":{"$ref":"AchievementUpdateMultipleResponse"},"scopes":["https://www.googleapis.com/auth/games"]}}},"applications":{"methods":{"get":{"flatPath":"games/v1/applications/{applicationId}","httpMethod":"GET","id":"games.applications.get","parameterOrder":["applicationId"],"parameters":{"applicationId":{"location":"path","required":true,"type":"string"},"language":{"location":"query","type":"string"},"platformType":{"enum":["ANDROID","IOS","WEB_APP"],"enumDescriptions":["Retrieve applications that can be played on Android.","Retrieve applications that can be played on iOS.","Retrieve applications that can be played on desktop web."],"location":"query","type":"string"}},"path":"games/v1/applications/{applicationId}","response":{"$ref":"Application"},"scopes":["https://www.googleapis.com/auth/games"]},"getEndPoint":{"flatPath":"games/v1/applications/getEndPoint","httpMethod":"POST","id":"games.applications.getEndPoint","parameterOrder":[],"parameters":{"applicationId":{"location":"query","type":"string"},"endPointType":{"enum":["PROFILE_CREATION","PROFILE_SETTINGS"],"enumDescriptions":["Request a URL to create a new profile.","Request a URL for the Settings view."],"location":"query","type":"string"}},"path":"games/v1/applications/getEndPoint","response":{"$ref":"EndPoint"},"scopes":["https://www.googleapis.com/auth/games"]},"played":{"flatPath":"games/v1/applications/played","httpMethod":"POST","id":"games.applications.played","parameterOrder":[],"parameters":{},"path":"games/v1/applications/played","scopes":["https://www.googleapis.com/auth/games"]},"verify":{"flatPath":"games/v1/applications/{applicationId}/verify","httpMethod":"GET","id":"games.applications.verify","parameterOrder":["applicationId"],"parameters":{"applicationId":{"location":"path","required":true,"type":"string"}},"path":"games/v1/applications/{applicationId}/verify","response":{"$ref":"ApplicationVerifyResponse"},"scopes":["https://www.googleapis.com/auth/games"]}}},"events":{"methods":{"listByPlayer":{"flatPath":"games/v1/events","httpMethod":"GET","id":"games.events.listByPlayer","parameterOrder":[],"parameters":{"language":{"location":"query","type":"string"},"maxResults":{"format":"int32","location":"query","type":"integer"},"pageToken":{"location":"query","type":"string"}},"path":"games/v1/events","response":{"$ref":"PlayerEventListResponse"},"scopes":["https://www.googleapis.com/auth/games"]},"listDefinitions":{"flatPath":"games/v1/eventDefinitions","httpMethod":"GET","id":"games.events.listDefinitions","parameterOrder":[],"parameters":{"language":{"location":"query","type":"string"},"maxResults":{"format":"int32","location":"query","type":"integer"},"pageToken":{"location":"query","type":"string"}},"path":"games/v1/eventDefinitions","response":{"$ref":"EventDefinitionListResponse"},"scopes":["https://www.googleapis.com/auth/games"]},"record":{"flatPath":"games/v1/events","httpMethod":"POST","id":"games.events.record","parameterOrder":[],"parameters":{"language":{"location":"query","type":"string"}},"path":"games/v1/events","request":{"$ref":"EventRecordRequest"},"response":{"$ref":"EventUpdateResponse"},"scopes":["https://www.googleapis.com/auth/games"]}}},"leaderboards":{"methods":{"get":{"flatPath":"games/v1/leaderboards/{leaderboardId}","httpMethod":"GET","id":"games.leaderboards.get","parameterOrder":["leaderboardId"],"parameters":{"language":{"location":"query","type":"string"},"leaderboardId":{"location":"path","required":true,"type":"string"}},"path":"games/v1/leaderboards/{leaderboardId}","response":{"$ref":"Leaderboard"},"scopes":["https://www.googleapis.com/auth/games"]},"list":{"flatPath":"games/v1/leaderboards","httpMethod":"GET","id":"games.leaderboards.list","parameterOrder":[],"parameters":{"language":{"location":"query","type":"string"},"maxResults":{"format":"int32","location":"query","type":"integer"},"pageToken":{"location":"query","type":"string"}},"path":"games/v1/leaderboards","response":{"$ref":"LeaderboardListResponse"},"scopes":["https://www.googleapis.com/auth/games"]}}},"metagame":{"methods":{"getMetagameConfig":{"flatPath":"games/v1/metagameConfig","httpMethod":"GET","id":"games.metagame.getMetagameConfig","parameterOrder":[],"parameters":{},"path":"games/v1/metagameConfig","response":{"$ref":"MetagameConfig"},"scopes":["https://www.googleapis.com/auth/games"]},"listCategoriesByPlayer":{"flatPath":"games/v1/players/{playerId}/categories/{collection}","httpMethod":"GET","id":"games.metagame.listCategoriesByPlayer","parameterOrder":["playerId","collection"],"parameters":{"collection":{"enum":["ALL"],"enumDescriptions":["Retrieve data for all categories. This is the default."],"location":"path","required":true,"type":"string"},"language":{"location":"query","type":"string"},"maxResults":{"format":"int32","location":"query","type":"integer"},"pageToken":{"location":"query","type":"string"},"playerId":{"location":"path","required":true,"type":"string"}},"path":"games/v1/players/{playerId}/categories/{collection}","response":{"$ref":"CategoryListResponse"},"scopes":["https://www.googleapis.com/auth/games"]}}},"players":{"methods":{"get":{"flatPath":"games/v1/players/{playerId}","httpMethod":"GET","id":"games.players.get","parameterOrder":["playerId"],"parameters":{"language":{"location":"query","type":"string"},"playerId":{"location":"path","required":true,"type":"string"},"playerIdConsistencyToken":{"location":"query","type":"string"}},"path":"games/v1/players/{playerId}","response":{"$ref":"Player"},"scopes":["https://www.googleapis.com/auth/games"]},"getMultipleApplicationPlayerIds":{"flatPath":"games/v1/players/me/multipleApplicationPlayerIds","httpMethod":"GET","id":"games.players.getMultipleApplicationPlayerIds","parameterOrder":[],"parameters":{"applicationIds":{"location":"query","repeated":true,"type":"string"}},"path":"games/v1/players/me/multipleApplicationPlayerIds","response":{"$ref":"GetMultipleApplicationPlayerIdsResponse"},"scopes":["https://www.googleapis.com/auth/games"]},"getScopedPlayerIds":{"flatPath":"games/v1/players/me/scopedIds","httpMethod":"GET","id":"games.players.getScopedPlayerIds","parameterOrder":[],"parameters":{},"path":"games/v1/players/me/scopedIds","response":{"$ref":"ScopedPlayerIds"},"scopes":["https://www.googleapis.com/auth/games"]},"list":{"flatPath":"games/v1/players/me/players/{collection}","httpMethod":"GET","id":"games.players.list","parameterOrder":["collection"],"parameters":{"collection":{"enum":["CONNECTED","VISIBLE","FRIENDS_ALL"],"enumDeprecated":[true,true,false],"enumDescriptions":["Retrieve a list of players that are also playing this game in reverse chronological order.","Retrieve a list of players in the user's social graph that are visible to this game.","Retrieve a list of players who are friends of the user in alphabetical order."],"location":"path","required":true,"type":"string"},"language":{"location":"query","type":"string"},"maxResults":{"format":"int32","location":"query","type":"integer"},"pageToken":{"location":"query","type":"string"}},"path":"games/v1/players/me/players/{collection}","response":{"$ref":"PlayerListResponse"},"scopes":["https://www.googleapis.com/auth/games"]}}},"recall":{"methods":{"gamesPlayerTokens":{"flatPath":"games/v1/recall/gamesPlayerTokens/{sessionId}","httpMethod":"GET","id":"games.recall.gamesPlayerTokens","parameterOrder":["sessionId"],"parameters":{"applicationIds":{"location":"query","repeated":true,"type":"string"},"sessionId":{"location":"path","required":true,"type":"string"}},"path":"games/v1/recall/gamesPlayerTokens/{sessionId}","response":{"$ref":"RetrieveGamesPlayerTokensResponse"},"scopes":["https://www.googleapis.com/auth/androidpublisher"]},"lastTokenFromAllDeveloperGames":{"flatPath":"games/v1/recall/developerGamesLastPlayerToken/{sessionId}","httpMethod":"GET","id":"games.recall.lastTokenFromAllDeveloperGames","parameterOrder":["sessionId"],"parameters":{"sessionId":{"location":"path","required":true,"type":"string"}},"path":"games/v1/recall/developerGamesLastPlayerToken/{sessionId}","response":{"$ref":"RetrieveDeveloperGamesLastPlayerTokenResponse"},"scopes":["https://www.googleapis.com/auth/androidpublisher"]},"linkPersona":{"flatPath":"games/v1/recall:linkPersona","httpMethod":"POST","id":"games.recall.linkPersona","parameterOrder":[],"parameters":{},"path":"games/v1/recall:linkPersona","request":{"$ref":"LinkPersonaRequest"},"response":{"$ref":"LinkPersonaResponse"},"scopes":["https://www.googleapis.com/auth/androidpublisher"]},"resetPersona":{"flatPath":"games/v1/recall:resetPersona","httpMethod":"POST","id":"games.recall.resetPersona","parameterOrder":[],"parameters":{},"path":"games/v1/recall:resetPersona","request":{"$ref":"ResetPersonaRequest"},"response":{"$ref":"ResetPersonaResponse"},"scopes":["https://www.googleapis.com/auth/androidpublisher"]},"retrieveTokens":{"flatPath":"games/v1/recall/tokens/{sessionId}","httpMethod":"GET","id":"games.recall.retrieveTokens","parameterOrder":["sessionId"],"parameters":{"sessionId":{"location":"path","required":true,"type":"string"}},"path":"games/v1/recall/tokens/{sessionId}","response":{"$ref":"RetrievePlayerTokensResponse"},"scopes":["https://www.googleapis.com/auth/androidpublisher"]},"unlinkPersona":{"flatPath":"games/v1/recall:unlinkPersona","httpMethod":"POST","id":"games.recall.unlinkPersona","parameterOrder":[],"parameters":{},"path":"games/v1/recall:unlinkPersona","request":{"$ref":"UnlinkPersonaRequest"},"response":{"$ref":"UnlinkPersonaResponse"},"scopes":["https://www.googleapis.com/auth/androidpublisher"]}}},"revisions":{"methods":{"check":{"flatPath":"games/v1/revisions/check","httpMethod":"GET","id":"games.revisions.check","parameterOrder":["clientRevision"],"parameters":{"clientRevision":{"location":"query","required":true,"type":"string"}},"path":"games/v1/revisions/check","response":{"$ref":"RevisionCheckResponse"},"scopes":["https://www.googleapis.com/auth/games"]}}},"scores":{"methods":{"get":{"flatPath":"games/v1/players/{playerId}/leaderboards/{leaderboardId}/scores/{timeSpan}","httpMethod":"GET","id":"games.scores.get","parameterOrder":["playerId","leaderboardId","timeSpan"],"parameters":{"includeRankType":{"enum":["ALL","PUBLIC","SOCIAL","FRIENDS"],"enumDeprecated":[false,false,true,false],"enumDescriptions":["Retrieve all supported ranks. In HTTP, this parameter value can also be specified as `ALL`.","Retrieve public ranks, if the player is sharing their gameplay activity publicly.","(Obsolete) Retrieve the social rank.","Retrieve the rank on the friends collection."],"location":"query","type":"string"},"language":{"location":"query","type":"string"},"leaderboardId":{"location":"path","required":true,"type":"string"},"maxResults":{"format":"int32","location":"query","type":"integer"},"pageToken":{"location":"query","type":"string"},"playerId":{"location":"path","required":true,"type":"string"},"timeSpan":{"enum":["ALL","ALL_TIME","WEEKLY","DAILY"],"enumDescriptions":["Get the high scores for all time spans. If this is used, maxResults values will be ignored.","Get the all time high score.","List the top scores for the current day.","List the top scores for the current week."],"location":"path","required":true,"type":"string"}},"path":"games/v1/players/{playerId}/leaderboards/{leaderboardId}/scores/{timeSpan}","response":{"$ref":"PlayerLeaderboardScoreListResponse"},"scopes":["https://www.googleapis.com/auth/games"]},"list":{"flatPath":"games/v1/leaderboards/{leaderboardId}/scores/{collection}","httpMethod":"GET","id":"games.scores.list","parameterOrder":["leaderboardId","collection","timeSpan"],"parameters":{"collection":{"enum":["PUBLIC","SOCIAL","FRIENDS"],"enumDeprecated":[false,true,false],"enumDescriptions":["List all scores in the public leaderboard.","(Obsolete) Legacy G+ social scores.","List only scores of friends."],"location":"path","required":true,"type":"string"},"language":{"location":"query","type":"string"},"leaderboardId":{"location":"path","required":true,"type":"string"},"maxResults":{"format":"int32","location":"query","type":"integer"},"pageToken":{"location":"query","type":"string"},"timeSpan":{"enum":["ALL_TIME","WEEKLY","DAILY"],"enumDescriptions":["The score is an all-time score.","The score is a weekly score.","The score is a daily score."],"location":"query","required":true,"type":"string"}},"path":"games/v1/leaderboards/{leaderboardId}/scores/{collection}","response":{"$ref":"LeaderboardScores"},"scopes":["https://www.googleapis.com/auth/games"]},"listWindow":{"flatPath":"games/v1/leaderboards/{leaderboardId}/window/{collection}","httpMethod":"GET","id":"games.scores.listWindow","parameterOrder":["leaderboardId","collection","timeSpan"],"parameters":{"collection":{"enum":["PUBLIC","SOCIAL","FRIENDS"],"enumDeprecated":[false,true,false],"enumDescriptions":["List all scores in the public leaderboard.","(Obsolete) Legacy G+ social scores.","List only scores of friends."],"location":"path","required":true,"type":"string"},"language":{"location":"query","type":"string"},"leaderboardId":{"location":"path","required":true,"type":"string"},"maxResults":{"format":"int32","location":"query","type":"integer"},"pageToken":{"location":"query","type":"string"},"resultsAbove":{"format":"int32","location":"query","type":"integer"},"returnTopIfAbsent":{"location":"query","type":"boolean"},"timeSpan":{"enum":["ALL_TIME","WEEKLY","DAILY"],"enumDescriptions":["The score is an all-time score.","The score is a weekly score.","The score is a daily score."],"location":"query","required":true,"type":"string"}},"path":"games/v1/leaderboards/{leaderboardId}/window/{collection}","response":{"$ref":"LeaderboardScores"},"scopes":["https://www.googleapis.com/auth/games"]},"submit":{"flatPath":"games/v1/leaderboards/{leaderboardId}/scores","httpMethod":"POST","id":"games.scores.submit","parameterOrder":["leaderboardId","score"],"parameters":{"language":{"location":"query","type":"string"},"leaderboardId":{"location":"path","required":true,"type":"string"},"score":{"format":"int64","location":"query","required":true,"type":"string"},"scoreTag":{"location":"query","pattern":"[a-zA-Z0-9-._~]{0,64}","type":"string"}},"path":"games/v1/leaderboards/{leaderboardId}/scores","response":{"$ref":"PlayerScoreResponse"},"scopes":["https://www.googleapis.com/auth/games"]},"submitMultiple":{"flatPath":"games/v1/leaderboards/scores","httpMethod":"POST","id":"games.scores.submitMultiple","parameterOrder":[],"parameters":{"language":{"location":"query","type":"string"}},"path":"games/v1/leaderboards/scores","request":{"$ref":"PlayerScoreSubmissionList"},"response":{"$ref":"PlayerScoreListResponse"},"scopes":["https://www.googleapis.com/auth/games"]}}},"snapshots":{"methods":{"get":{"flatPath":"games/v1/snapshots/{snapshotId}","httpMethod":"GET","id":"games.snapshots.get","parameterOrder":["snapshotId"],"parameters":{"language":{"location":"query","type":"string"},"snapshotId":{"location":"path","required":true,"type":"string"}},"path":"games/v1/snapshots/{snapshotId}","response":{"$ref":"Snapshot"},"scopes":["https://www.googleapis.com/auth/drive.appdata","https://www.googleapis.com/auth/games"]},"list":{"flatPath":"games/v1/players/{playerId}/snapshots","httpMethod":"GET","id":"games.snapshots.list","parameterOrder":["playerId"],"parameters":{"language":{"location":"query","type":"string"},"maxResults":{"format":"int32","location":"query","type":"integer"},"pageToken":{"location":"query","type":"string"},"playerId":{"location":"path","required":true,"type":"string"}},"path":"games/v1/players/{playerId}/snapshots","response":{"$ref":"SnapshotListResponse"},"scopes":["https://www.googleapis.com/auth/drive.appdata","https://www.googleapis.com/auth/games"]}}},"stats":{"methods":{"get":{"flatPath":"games/v1/stats","httpMethod":"GET","id":"games.stats.get","parameterOrder":[],"parameters":{},"path":"games/v1/stats","response":{"$ref":"StatsResponse"},"scopes":["https://www.googleapis.com/auth/games"]}}}}}
