{"basePath":"","rootUrl":"https://gkehub.googleapis.com/","resources":{"projects":{"resources":{"locations":{"methods":{"get":{"flatPath":"v1beta1/projects/{projectsId}/locations/{locationsId}","httpMethod":"GET","id":"gkehub.projects.locations.get","parameterOrder":["name"],"parameters":{"name":{"location":"path","pattern":"^projects/[^/]+/locations/[^/]+$","required":true,"type":"string"}},"path":"v1beta1/{+name}","response":{"$ref":"Location"},"scopes":["https://www.googleapis.com/auth/cloud-platform"]},"list":{"flatPath":"v1beta1/projects/{projectsId}/locations","httpMethod":"GET","id":"gkehub.projects.locations.list","parameterOrder":["name"],"parameters":{"extraLocationTypes":{"location":"query","repeated":true,"type":"string"},"filter":{"location":"query","type":"string"},"name":{"location":"path","pattern":"^projects/[^/]+$","required":true,"type":"string"},"pageSize":{"format":"int32","location":"query","type":"integer"},"pageToken":{"location":"query","type":"string"}},"path":"v1beta1/{+name}/locations","response":{"$ref":"ListLocationsResponse"},"scopes":["https://www.googleapis.com/auth/cloud-platform"]}},"resources":{"memberships":{"methods":{"create":{"flatPath":"v1beta1/projects/{projectsId}/locations/{locationsId}/memberships","httpMethod":"POST","id":"gkehub.projects.locations.memberships.create","parameterOrder":["parent"],"parameters":{"membershipId":{"location":"query","type":"string"},"parent":{"location":"path","pattern":"^projects/[^/]+/locations/[^/]+$","required":true,"type":"string"},"requestId":{"location":"query","type":"string"}},"path":"v1beta1/{+parent}/memberships","request":{"$ref":"Membership"},"response":{"$ref":"Operation"},"scopes":["https://www.googleapis.com/auth/cloud-platform"]},"delete":{"flatPath":"v1beta1/projects/{projectsId}/locations/{locationsId}/memberships/{membershipsId}","httpMethod":"DELETE","id":"gkehub.projects.locations.memberships.delete","parameterOrder":["name"],"parameters":{"force":{"location":"query","type":"boolean"},"name":{"location":"path","pattern":"^projects/[^/]+/locations/[^/]+/memberships/[^/]+$","required":true,"type":"string"},"requestId":{"location":"query","type":"string"}},"path":"v1beta1/{+name}","response":{"$ref":"Operation"},"scopes":["https://www.googleapis.com/auth/cloud-platform"]},"generateConnectManifest":{"flatPath":"v1beta1/projects/{projectsId}/locations/{locationsId}/memberships/{membershipsId}:generateConnectManifest","httpMethod":"GET","id":"gkehub.projects.locations.memberships.generateConnectManifest","parameterOrder":["name"],"parameters":{"connectAgent.name":{"deprecated":true,"location":"query","type":"string"},"connectAgent.namespace":{"location":"query","type":"string"},"connectAgent.proxy":{"format":"byte","location":"query","type":"string"},"imagePullSecretContent":{"format":"byte","location":"query","type":"string"},"isUpgrade":{"location":"query","type":"boolean"},"name":{"location":"path","pattern":"^projects/[^/]+/locations/[^/]+/memberships/[^/]+$","required":true,"type":"string"},"registry":{"location":"query","type":"string"},"version":{"location":"query","type":"string"}},"path":"v1beta1/{+name}:generateConnectManifest","response":{"$ref":"GenerateConnectManifestResponse"},"scopes":["https://www.googleapis.com/auth/cloud-platform"]},"generateExclusivityManifest":{"flatPath":"v1beta1/projects/{projectsId}/locations/{locationsId}/memberships/{membershipsId}:generateExclusivityManifest","httpMethod":"GET","id":"gkehub.projects.locations.memberships.generateExclusivityManifest","parameterOrder":["name"],"parameters":{"crManifest":{"location":"query","type":"string"},"crdManifest":{"location":"query","type":"string"},"name":{"location":"path","pattern":"^projects/[^/]+/locations/[^/]+/memberships/[^/]+$","required":true,"type":"string"}},"path":"v1beta1/{+name}:generateExclusivityManifest","response":{"$ref":"GenerateExclusivityManifestResponse"},"scopes":["https://www.googleapis.com/auth/cloud-platform"]},"get":{"flatPath":"v1beta1/projects/{projectsId}/locations/{locationsId}/memberships/{membershipsId}","httpMethod":"GET","id":"gkehub.projects.locations.memberships.get","parameterOrder":["name"],"parameters":{"name":{"location":"path","pattern":"^projects/[^/]+/locations/[^/]+/memberships/[^/]+$","required":true,"type":"string"}},"path":"v1beta1/{+name}","response":{"$ref":"Membership"},"scopes":["https://www.googleapis.com/auth/cloud-platform"]},"getIamPolicy":{"flatPath":"v1beta1/projects/{projectsId}/locations/{locationsId}/memberships/{membershipsId}:getIamPolicy","httpMethod":"GET","id":"gkehub.projects.locations.memberships.getIamPolicy","parameterOrder":["resource"],"parameters":{"options.requestedPolicyVersion":{"format":"int32","location":"query","type":"integer"},"resource":{"location":"path","pattern":"^projects/[^/]+/locations/[^/]+/memberships/[^/]+$","required":true,"type":"string"}},"path":"v1beta1/{+resource}:getIamPolicy","response":{"$ref":"Policy"},"scopes":["https://www.googleapis.com/auth/cloud-platform"]},"list":{"flatPath":"v1beta1/projects/{projectsId}/locations/{locationsId}/memberships","httpMethod":"GET","id":"gkehub.projects.locations.memberships.list","parameterOrder":["parent"],"parameters":{"filter":{"location":"query","type":"string"},"orderBy":{"location":"query","type":"string"},"pageSize":{"format":"int32","location":"query","type":"integer"},"pageToken":{"location":"query","type":"string"},"parent":{"location":"path","pattern":"^projects/[^/]+/locations/[^/]+$","required":true,"type":"string"}},"path":"v1beta1/{+parent}/memberships","response":{"$ref":"ListMembershipsResponse"},"scopes":["https://www.googleapis.com/auth/cloud-platform"]},"patch":{"flatPath":"v1beta1/projects/{projectsId}/locations/{locationsId}/memberships/{membershipsId}","httpMethod":"PATCH","id":"gkehub.projects.locations.memberships.patch","parameterOrder":["name"],"parameters":{"name":{"location":"path","pattern":"^projects/[^/]+/locations/[^/]+/memberships/[^/]+$","required":true,"type":"string"},"requestId":{"location":"query","type":"string"},"updateMask":{"format":"google-fieldmask","location":"query","type":"string"}},"path":"v1beta1/{+name}","request":{"$ref":"Membership"},"response":{"$ref":"Operation"},"scopes":["https://www.googleapis.com/auth/cloud-platform"]},"setIamPolicy":{"flatPath":"v1beta1/projects/{projectsId}/locations/{locationsId}/memberships/{membershipsId}:setIamPolicy","httpMethod":"POST","id":"gkehub.projects.locations.memberships.setIamPolicy","parameterOrder":["resource"],"parameters":{"resource":{"location":"path","pattern":"^projects/[^/]+/locations/[^/]+/memberships/[^/]+$","required":true,"type":"string"}},"path":"v1beta1/{+resource}:setIamPolicy","request":{"$ref":"SetIamPolicyRequest"},"response":{"$ref":"Policy"},"scopes":["https://www.googleapis.com/auth/cloud-platform"]},"testIamPermissions":{"flatPath":"v1beta1/projects/{projectsId}/locations/{locationsId}/memberships/{membershipsId}:testIamPermissions","httpMethod":"POST","id":"gkehub.projects.locations.memberships.testIamPermissions","parameterOrder":["resource"],"parameters":{"resource":{"location":"path","pattern":"^projects/[^/]+/locations/[^/]+/memberships/[^/]+$","required":true,"type":"string"}},"path":"v1beta1/{+resource}:testIamPermissions","request":{"$ref":"TestIamPermissionsRequest"},"response":{"$ref":"TestIamPermissionsResponse"},"scopes":["https://www.googleapis.com/auth/cloud-platform"]},"validateExclusivity":{"flatPath":"v1beta1/projects/{projectsId}/locations/{locationsId}/memberships:validateExclusivity","httpMethod":"GET","id":"gkehub.projects.locations.memberships.validateExclusivity","parameterOrder":["parent"],"parameters":{"crManifest":{"location":"query","type":"string"},"intendedMembership":{"location":"query","type":"string"},"parent":{"location":"path","pattern":"^projects/[^/]+/locations/[^/]+$","required":true,"type":"string"}},"path":"v1beta1/{+parent}/memberships:validateExclusivity","response":{"$ref":"ValidateExclusivityResponse"},"scopes":["https://www.googleapis.com/auth/cloud-platform"]}}},"operations":{"methods":{"cancel":{"flatPath":"v1beta1/projects/{projectsId}/locations/{locationsId}/operations/{operationsId}:cancel","httpMethod":"POST","id":"gkehub.projects.locations.operations.cancel","parameterOrder":["name"],"parameters":{"name":{"location":"path","pattern":"^projects/[^/]+/locations/[^/]+/operations/[^/]+$","required":true,"type":"string"}},"path":"v1beta1/{+name}:cancel","request":{"$ref":"CancelOperationRequest"},"response":{"$ref":"Empty"},"scopes":["https://www.googleapis.com/auth/cloud-platform"]},"delete":{"flatPath":"v1beta1/projects/{projectsId}/locations/{locationsId}/operations/{operationsId}","httpMethod":"DELETE","id":"gkehub.projects.locations.operations.delete","parameterOrder":["name"],"parameters":{"name":{"location":"path","pattern":"^projects/[^/]+/locations/[^/]+/operations/[^/]+$","required":true,"type":"string"}},"path":"v1beta1/{+name}","response":{"$ref":"Empty"},"scopes":["https://www.googleapis.com/auth/cloud-platform"]},"get":{"flatPath":"v1beta1/projects/{projectsId}/locations/{locationsId}/operations/{operationsId}","httpMethod":"GET","id":"gkehub.projects.locations.operations.get","parameterOrder":["name"],"parameters":{"name":{"location":"path","pattern":"^projects/[^/]+/locations/[^/]+/operations/[^/]+$","required":true,"type":"string"}},"path":"v1beta1/{+name}","response":{"$ref":"Operation"},"scopes":["https://www.googleapis.com/auth/cloud-platform"]},"list":{"flatPath":"v1beta1/projects/{projectsId}/locations/{locationsId}/operations","httpMethod":"GET","id":"gkehub.projects.locations.operations.list","parameterOrder":["name"],"parameters":{"filter":{"location":"query","type":"string"},"name":{"location":"path","pattern":"^projects/[^/]+/locations/[^/]+$","required":true,"type":"string"},"pageSize":{"format":"int32","location":"query","type":"integer"},"pageToken":{"location":"query","type":"string"},"returnPartialSuccess":{"location":"query","type":"boolean"}},"path":"v1beta1/{+name}/operations","response":{"$ref":"ListOperationsResponse"},"scopes":["https://www.googleapis.com/auth/cloud-platform"]}}}}}}}}}
