{"basePath":"/identitytoolkit/v3/relyingparty/","rootUrl":"https://www.googleapis.com/","resources":{"relyingparty":{"methods":{"createAuthUri":{"httpMethod":"POST","id":"identitytoolkit.relyingparty.createAuthUri","path":"createAuthUri","request":{"$ref":"IdentitytoolkitRelyingpartyCreateAuthUriRequest"},"response":{"$ref":"CreateAuthUriResponse"},"scopes":["https://www.googleapis.com/auth/cloud-platform"]},"deleteAccount":{"httpMethod":"POST","id":"identitytoolkit.relyingparty.deleteAccount","path":"deleteAccount","request":{"$ref":"IdentitytoolkitRelyingpartyDeleteAccountRequest"},"response":{"$ref":"DeleteAccountResponse"},"scopes":["https://www.googleapis.com/auth/cloud-platform"]},"downloadAccount":{"httpMethod":"POST","id":"identitytoolkit.relyingparty.downloadAccount","path":"downloadAccount","request":{"$ref":"IdentitytoolkitRelyingpartyDownloadAccountRequest"},"response":{"$ref":"DownloadAccountResponse"},"scopes":["https://www.googleapis.com/auth/cloud-platform","https://www.googleapis.com/auth/firebase"]},"emailLinkSignin":{"httpMethod":"POST","id":"identitytoolkit.relyingparty.emailLinkSignin","path":"emailLinkSignin","request":{"$ref":"IdentitytoolkitRelyingpartyEmailLinkSigninRequest"},"response":{"$ref":"EmailLinkSigninResponse"},"scopes":["https://www.googleapis.com/auth/cloud-platform"]},"getAccountInfo":{"httpMethod":"POST","id":"identitytoolkit.relyingparty.getAccountInfo","path":"getAccountInfo","request":{"$ref":"IdentitytoolkitRelyingpartyGetAccountInfoRequest"},"response":{"$ref":"GetAccountInfoResponse"},"scopes":["https://www.googleapis.com/auth/cloud-platform"]},"getOobConfirmationCode":{"httpMethod":"POST","id":"identitytoolkit.relyingparty.getOobConfirmationCode","path":"getOobConfirmationCode","request":{"$ref":"Relyingparty"},"response":{"$ref":"GetOobConfirmationCodeResponse"},"scopes":["https://www.googleapis.com/auth/cloud-platform"]},"getProjectConfig":{"httpMethod":"GET","id":"identitytoolkit.relyingparty.getProjectConfig","parameters":{"delegatedProjectNumber":{"location":"query","type":"string"},"projectNumber":{"location":"query","type":"string"}},"path":"getProjectConfig","response":{"$ref":"IdentitytoolkitRelyingpartyGetProjectConfigResponse"},"scopes":["https://www.googleapis.com/auth/cloud-platform"]},"getPublicKeys":{"httpMethod":"GET","id":"identitytoolkit.relyingparty.getPublicKeys","path":"publicKeys","response":{"$ref":"IdentitytoolkitRelyingpartyGetPublicKeysResponse"},"scopes":["https://www.googleapis.com/auth/cloud-platform"]},"getRecaptchaParam":{"httpMethod":"GET","id":"identitytoolkit.relyingparty.getRecaptchaParam","path":"getRecaptchaParam","response":{"$ref":"GetRecaptchaParamResponse"},"scopes":["https://www.googleapis.com/auth/cloud-platform"]},"resetPassword":{"httpMethod":"POST","id":"identitytoolkit.relyingparty.resetPassword","path":"resetPassword","request":{"$ref":"IdentitytoolkitRelyingpartyResetPasswordRequest"},"response":{"$ref":"ResetPasswordResponse"},"scopes":["https://www.googleapis.com/auth/cloud-platform"]},"sendVerificationCode":{"httpMethod":"POST","id":"identitytoolkit.relyingparty.sendVerificationCode","path":"sendVerificationCode","request":{"$ref":"IdentitytoolkitRelyingpartySendVerificationCodeRequest"},"response":{"$ref":"IdentitytoolkitRelyingpartySendVerificationCodeResponse"},"scopes":["https://www.googleapis.com/auth/cloud-platform"]},"setAccountInfo":{"httpMethod":"POST","id":"identitytoolkit.relyingparty.setAccountInfo","path":"setAccountInfo","request":{"$ref":"IdentitytoolkitRelyingpartySetAccountInfoRequest"},"response":{"$ref":"SetAccountInfoResponse"},"scopes":["https://www.googleapis.com/auth/cloud-platform"]},"setProjectConfig":{"httpMethod":"POST","id":"identitytoolkit.relyingparty.setProjectConfig","path":"setProjectConfig","request":{"$ref":"IdentitytoolkitRelyingpartySetProjectConfigRequest"},"response":{"$ref":"IdentitytoolkitRelyingpartySetProjectConfigResponse"},"scopes":["https://www.googleapis.com/auth/cloud-platform"]},"signOutUser":{"httpMethod":"POST","id":"identitytoolkit.relyingparty.signOutUser","path":"signOutUser","request":{"$ref":"IdentitytoolkitRelyingpartySignOutUserRequest"},"response":{"$ref":"IdentitytoolkitRelyingpartySignOutUserResponse"},"scopes":["https://www.googleapis.com/auth/cloud-platform"]},"signupNewUser":{"httpMethod":"POST","id":"identitytoolkit.relyingparty.signupNewUser","path":"signupNewUser","request":{"$ref":"IdentitytoolkitRelyingpartySignupNewUserRequest"},"response":{"$ref":"SignupNewUserResponse"},"scopes":["https://www.googleapis.com/auth/cloud-platform"]},"uploadAccount":{"httpMethod":"POST","id":"identitytoolkit.relyingparty.uploadAccount","path":"uploadAccount","request":{"$ref":"IdentitytoolkitRelyingpartyUploadAccountRequest"},"response":{"$ref":"UploadAccountResponse"},"scopes":["https://www.googleapis.com/auth/cloud-platform","https://www.googleapis.com/auth/firebase"]},"verifyAssertion":{"httpMethod":"POST","id":"identitytoolkit.relyingparty.verifyAssertion","path":"verifyAssertion","request":{"$ref":"IdentitytoolkitRelyingpartyVerifyAssertionRequest"},"response":{"$ref":"VerifyAssertionResponse"},"scopes":["https://www.googleapis.com/auth/cloud-platform"]},"verifyCustomToken":{"httpMethod":"POST","id":"identitytoolkit.relyingparty.verifyCustomToken","path":"verifyCustomToken","request":{"$ref":"IdentitytoolkitRelyingpartyVerifyCustomTokenRequest"},"response":{"$ref":"VerifyCustomTokenResponse"},"scopes":["https://www.googleapis.com/auth/cloud-platform"]},"verifyPassword":{"httpMethod":"POST","id":"identitytoolkit.relyingparty.verifyPassword","path":"verifyPassword","request":{"$ref":"IdentitytoolkitRelyingpartyVerifyPasswordRequest"},"response":{"$ref":"VerifyPasswordResponse"},"scopes":["https://www.googleapis.com/auth/cloud-platform"]},"verifyPhoneNumber":{"httpMethod":"POST","id":"identitytoolkit.relyingparty.verifyPhoneNumber","path":"verifyPhoneNumber","request":{"$ref":"IdentitytoolkitRelyingpartyVerifyPhoneNumberRequest"},"response":{"$ref":"IdentitytoolkitRelyingpartyVerifyPhoneNumberResponse"},"scopes":["https://www.googleapis.com/auth/cloud-platform"]}}}}}
