{"basePath":"","rootUrl":"https://containeranalysis.googleapis.com/","resources":{"projects":{"resources":{"locations":{"resources":{"notes":{"methods":{"batchCreate":{"flatPath":"v1beta1/projects/{projectsId}/locations/{locationsId}/notes:batchCreate","httpMethod":"POST","id":"containeranalysis.projects.locations.notes.batchCreate","parameterOrder":["parent"],"parameters":{"parent":{"location":"path","pattern":"^projects/[^/]+/locations/[^/]+$","required":true,"type":"string"}},"path":"v1beta1/{+parent}/notes:batchCreate","request":{"$ref":"BatchCreateNotesRequest"},"response":{"$ref":"BatchCreateNotesResponse"},"scopes":["https://www.googleapis.com/auth/cloud-platform"]},"create":{"flatPath":"v1beta1/projects/{projectsId}/locations/{locationsId}/notes","httpMethod":"POST","id":"containeranalysis.projects.locations.notes.create","parameterOrder":["parent"],"parameters":{"noteId":{"location":"query","type":"string"},"parent":{"location":"path","pattern":"^projects/[^/]+/locations/[^/]+$","required":true,"type":"string"}},"path":"v1beta1/{+parent}/notes","request":{"$ref":"Note"},"response":{"$ref":"Note"},"scopes":["https://www.googleapis.com/auth/cloud-platform"]},"delete":{"flatPath":"v1beta1/projects/{projectsId}/locations/{locationsId}/notes/{notesId}","httpMethod":"DELETE","id":"containeranalysis.projects.locations.notes.delete","parameterOrder":["name"],"parameters":{"name":{"location":"path","pattern":"^projects/[^/]+/locations/[^/]+/notes/[^/]+$","required":true,"type":"string"}},"path":"v1beta1/{+name}","response":{"$ref":"Empty"},"scopes":["https://www.googleapis.com/auth/cloud-platform"]},"get":{"flatPath":"v1beta1/projects/{projectsId}/locations/{locationsId}/notes/{notesId}","httpMethod":"GET","id":"containeranalysis.projects.locations.notes.get","parameterOrder":["name"],"parameters":{"name":{"location":"path","pattern":"^projects/[^/]+/locations/[^/]+/notes/[^/]+$","required":true,"type":"string"}},"path":"v1beta1/{+name}","response":{"$ref":"Note"},"scopes":["https://www.googleapis.com/auth/cloud-platform"]},"getIamPolicy":{"flatPath":"v1beta1/projects/{projectsId}/locations/{locationsId}/notes/{notesId}:getIamPolicy","httpMethod":"POST","id":"containeranalysis.projects.locations.notes.getIamPolicy","parameterOrder":["resource"],"parameters":{"resource":{"location":"path","pattern":"^projects/[^/]+/locations/[^/]+/notes/[^/]+$","required":true,"type":"string"}},"path":"v1beta1/{+resource}:getIamPolicy","request":{"$ref":"GetIamPolicyRequest"},"response":{"$ref":"Policy"},"scopes":["https://www.googleapis.com/auth/cloud-platform"]},"list":{"flatPath":"v1beta1/projects/{projectsId}/locations/{locationsId}/notes","httpMethod":"GET","id":"containeranalysis.projects.locations.notes.list","parameterOrder":["parent"],"parameters":{"filter":{"location":"query","type":"string"},"pageSize":{"format":"int32","location":"query","type":"integer"},"pageToken":{"location":"query","type":"string"},"parent":{"location":"path","pattern":"^projects/[^/]+/locations/[^/]+$","required":true,"type":"string"},"returnPartialSuccess":{"location":"query","type":"boolean"}},"path":"v1beta1/{+parent}/notes","response":{"$ref":"ListNotesResponse"},"scopes":["https://www.googleapis.com/auth/cloud-platform"]},"patch":{"flatPath":"v1beta1/projects/{projectsId}/locations/{locationsId}/notes/{notesId}","httpMethod":"PATCH","id":"containeranalysis.projects.locations.notes.patch","parameterOrder":["name"],"parameters":{"name":{"location":"path","pattern":"^projects/[^/]+/locations/[^/]+/notes/[^/]+$","required":true,"type":"string"},"updateMask":{"format":"google-fieldmask","location":"query","type":"string"}},"path":"v1beta1/{+name}","request":{"$ref":"Note"},"response":{"$ref":"Note"},"scopes":["https://www.googleapis.com/auth/cloud-platform"]},"setIamPolicy":{"flatPath":"v1beta1/projects/{projectsId}/locations/{locationsId}/notes/{notesId}:setIamPolicy","httpMethod":"POST","id":"containeranalysis.projects.locations.notes.setIamPolicy","parameterOrder":["resource"],"parameters":{"resource":{"location":"path","pattern":"^projects/[^/]+/locations/[^/]+/notes/[^/]+$","required":true,"type":"string"}},"path":"v1beta1/{+resource}:setIamPolicy","request":{"$ref":"SetIamPolicyRequest"},"response":{"$ref":"Policy"},"scopes":["https://www.googleapis.com/auth/cloud-platform"]},"testIamPermissions":{"flatPath":"v1beta1/projects/{projectsId}/locations/{locationsId}/notes/{notesId}:testIamPermissions","httpMethod":"POST","id":"containeranalysis.projects.locations.notes.testIamPermissions","parameterOrder":["resource"],"parameters":{"resource":{"location":"path","pattern":"^projects/[^/]+/locations/[^/]+/notes/[^/]+$","required":true,"type":"string"}},"path":"v1beta1/{+resource}:testIamPermissions","request":{"$ref":"TestIamPermissionsRequest"},"response":{"$ref":"TestIamPermissionsResponse"},"scopes":["https://www.googleapis.com/auth/cloud-platform"]}},"resources":{"occurrences":{"methods":{"list":{"flatPath":"v1beta1/projects/{projectsId}/locations/{locationsId}/notes/{notesId}/occurrences","httpMethod":"GET","id":"containeranalysis.projects.locations.notes.occurrences.list","parameterOrder":["name"],"parameters":{"filter":{"location":"query","type":"string"},"name":{"location":"path","pattern":"^projects/[^/]+/locations/[^/]+/notes/[^/]+$","required":true,"type":"string"},"pageSize":{"format":"int32","location":"query","type":"integer"},"pageToken":{"location":"query","type":"string"}},"path":"v1beta1/{+name}/occurrences","response":{"$ref":"ListNoteOccurrencesResponse"},"scopes":["https://www.googleapis.com/auth/cloud-platform"]}}}}},"occurrences":{"methods":{"batchCreate":{"flatPath":"v1beta1/projects/{projectsId}/locations/{locationsId}/occurrences:batchCreate","httpMethod":"POST","id":"containeranalysis.projects.locations.occurrences.batchCreate","parameterOrder":["parent"],"parameters":{"parent":{"location":"path","pattern":"^projects/[^/]+/locations/[^/]+$","required":true,"type":"string"}},"path":"v1beta1/{+parent}/occurrences:batchCreate","request":{"$ref":"BatchCreateOccurrencesRequest"},"response":{"$ref":"BatchCreateOccurrencesResponse"},"scopes":["https://www.googleapis.com/auth/cloud-platform"]},"create":{"flatPath":"v1beta1/projects/{projectsId}/locations/{locationsId}/occurrences","httpMethod":"POST","id":"containeranalysis.projects.locations.occurrences.create","parameterOrder":["parent"],"parameters":{"parent":{"location":"path","pattern":"^projects/[^/]+/locations/[^/]+$","required":true,"type":"string"}},"path":"v1beta1/{+parent}/occurrences","request":{"$ref":"Occurrence"},"response":{"$ref":"Occurrence"},"scopes":["https://www.googleapis.com/auth/cloud-platform"]},"delete":{"flatPath":"v1beta1/projects/{projectsId}/locations/{locationsId}/occurrences/{occurrencesId}","httpMethod":"DELETE","id":"containeranalysis.projects.locations.occurrences.delete","parameterOrder":["name"],"parameters":{"name":{"location":"path","pattern":"^projects/[^/]+/locations/[^/]+/occurrences/[^/]+$","required":true,"type":"string"}},"path":"v1beta1/{+name}","response":{"$ref":"Empty"},"scopes":["https://www.googleapis.com/auth/cloud-platform"]},"get":{"flatPath":"v1beta1/projects/{projectsId}/locations/{locationsId}/occurrences/{occurrencesId}","httpMethod":"GET","id":"containeranalysis.projects.locations.occurrences.get","parameterOrder":["name"],"parameters":{"name":{"location":"path","pattern":"^projects/[^/]+/locations/[^/]+/occurrences/[^/]+$","required":true,"type":"string"}},"path":"v1beta1/{+name}","response":{"$ref":"Occurrence"},"scopes":["https://www.googleapis.com/auth/cloud-platform"]},"getIamPolicy":{"flatPath":"v1beta1/projects/{projectsId}/locations/{locationsId}/occurrences/{occurrencesId}:getIamPolicy","httpMethod":"POST","id":"containeranalysis.projects.locations.occurrences.getIamPolicy","parameterOrder":["resource"],"parameters":{"resource":{"location":"path","pattern":"^projects/[^/]+/locations/[^/]+/occurrences/[^/]+$","required":true,"type":"string"}},"path":"v1beta1/{+resource}:getIamPolicy","request":{"$ref":"GetIamPolicyRequest"},"response":{"$ref":"Policy"},"scopes":["https://www.googleapis.com/auth/cloud-platform"]},"getNotes":{"flatPath":"v1beta1/projects/{projectsId}/locations/{locationsId}/occurrences/{occurrencesId}/notes","httpMethod":"GET","id":"containeranalysis.projects.locations.occurrences.getNotes","parameterOrder":["name"],"parameters":{"name":{"location":"path","pattern":"^projects/[^/]+/locations/[^/]+/occurrences/[^/]+$","required":true,"type":"string"}},"path":"v1beta1/{+name}/notes","response":{"$ref":"Note"},"scopes":["https://www.googleapis.com/auth/cloud-platform"]},"getVulnerabilitySummary":{"flatPath":"v1beta1/projects/{projectsId}/locations/{locationsId}/occurrences:vulnerabilitySummary","httpMethod":"GET","id":"containeranalysis.projects.locations.occurrences.getVulnerabilitySummary","parameterOrder":["parent"],"parameters":{"filter":{"location":"query","type":"string"},"parent":{"location":"path","pattern":"^projects/[^/]+/locations/[^/]+$","required":true,"type":"string"},"returnPartialSuccess":{"location":"query","type":"boolean"}},"path":"v1beta1/{+parent}/occurrences:vulnerabilitySummary","response":{"$ref":"VulnerabilityOccurrencesSummary"},"scopes":["https://www.googleapis.com/auth/cloud-platform"]},"list":{"flatPath":"v1beta1/projects/{projectsId}/locations/{locationsId}/occurrences","httpMethod":"GET","id":"containeranalysis.projects.locations.occurrences.list","parameterOrder":["parent"],"parameters":{"filter":{"location":"query","type":"string"},"pageSize":{"format":"int32","location":"query","type":"integer"},"pageToken":{"location":"query","type":"string"},"parent":{"location":"path","pattern":"^projects/[^/]+/locations/[^/]+$","required":true,"type":"string"},"returnPartialSuccess":{"location":"query","type":"boolean"}},"path":"v1beta1/{+parent}/occurrences","response":{"$ref":"ListOccurrencesResponse"},"scopes":["https://www.googleapis.com/auth/cloud-platform"]},"patch":{"flatPath":"v1beta1/projects/{projectsId}/locations/{locationsId}/occurrences/{occurrencesId}","httpMethod":"PATCH","id":"containeranalysis.projects.locations.occurrences.patch","parameterOrder":["name"],"parameters":{"name":{"location":"path","pattern":"^projects/[^/]+/locations/[^/]+/occurrences/[^/]+$","required":true,"type":"string"},"updateMask":{"format":"google-fieldmask","location":"query","type":"string"}},"path":"v1beta1/{+name}","request":{"$ref":"Occurrence"},"response":{"$ref":"Occurrence"},"scopes":["https://www.googleapis.com/auth/cloud-platform"]},"setIamPolicy":{"flatPath":"v1beta1/projects/{projectsId}/locations/{locationsId}/occurrences/{occurrencesId}:setIamPolicy","httpMethod":"POST","id":"containeranalysis.projects.locations.occurrences.setIamPolicy","parameterOrder":["resource"],"parameters":{"resource":{"location":"path","pattern":"^projects/[^/]+/locations/[^/]+/occurrences/[^/]+$","required":true,"type":"string"}},"path":"v1beta1/{+resource}:setIamPolicy","request":{"$ref":"SetIamPolicyRequest"},"response":{"$ref":"Policy"},"scopes":["https://www.googleapis.com/auth/cloud-platform"]},"testIamPermissions":{"flatPath":"v1beta1/projects/{projectsId}/locations/{locationsId}/occurrences/{occurrencesId}:testIamPermissions","httpMethod":"POST","id":"containeranalysis.projects.locations.occurrences.testIamPermissions","parameterOrder":["resource"],"parameters":{"resource":{"location":"path","pattern":"^projects/[^/]+/locations/[^/]+/occurrences/[^/]+$","required":true,"type":"string"}},"path":"v1beta1/{+resource}:testIamPermissions","request":{"$ref":"TestIamPermissionsRequest"},"response":{"$ref":"TestIamPermissionsResponse"},"scopes":["https://www.googleapis.com/auth/cloud-platform"]}}},"resources":{"methods":{"exportSBOM":{"flatPath":"v1beta1/projects/{projectsId}/locations/{locationsId}/resources/{resourcesId}:exportSBOM","httpMethod":"POST","id":"containeranalysis.projects.locations.resources.exportSBOM","parameterOrder":["name"],"parameters":{"name":{"location":"path","pattern":"^projects/[^/]+/locations/[^/]+/resources/.*$","required":true,"type":"string"}},"path":"v1beta1/{+name}:exportSBOM","request":{"$ref":"ExportSBOMRequest"},"response":{"$ref":"ExportSBOMResponse"},"scopes":["https://www.googleapis.com/auth/cloud-platform"]},"generatePackagesSummary":{"flatPath":"v1beta1/projects/{projectsId}/locations/{locationsId}/resources/{resourcesId}:generatePackagesSummary","httpMethod":"POST","id":"containeranalysis.projects.locations.resources.generatePackagesSummary","parameterOrder":["name"],"parameters":{"name":{"location":"path","pattern":"^projects/[^/]+/locations/[^/]+/resources/.*$","required":true,"type":"string"}},"path":"v1beta1/{+name}:generatePackagesSummary","request":{"$ref":"GeneratePackagesSummaryRequest"},"response":{"$ref":"PackagesSummaryResponse"},"scopes":["https://www.googleapis.com/auth/cloud-platform"]}}}}},"notes":{"methods":{"batchCreate":{"flatPath":"v1beta1/projects/{projectsId}/notes:batchCreate","httpMethod":"POST","id":"containeranalysis.projects.notes.batchCreate","parameterOrder":["parent"],"parameters":{"parent":{"location":"path","pattern":"^projects/[^/]+$","required":true,"type":"string"}},"path":"v1beta1/{+parent}/notes:batchCreate","request":{"$ref":"BatchCreateNotesRequest"},"response":{"$ref":"BatchCreateNotesResponse"},"scopes":["https://www.googleapis.com/auth/cloud-platform"]},"create":{"flatPath":"v1beta1/projects/{projectsId}/notes","httpMethod":"POST","id":"containeranalysis.projects.notes.create","parameterOrder":["parent"],"parameters":{"noteId":{"location":"query","type":"string"},"parent":{"location":"path","pattern":"^projects/[^/]+$","required":true,"type":"string"}},"path":"v1beta1/{+parent}/notes","request":{"$ref":"Note"},"response":{"$ref":"Note"},"scopes":["https://www.googleapis.com/auth/cloud-platform"]},"delete":{"flatPath":"v1beta1/projects/{projectsId}/notes/{notesId}","httpMethod":"DELETE","id":"containeranalysis.projects.notes.delete","parameterOrder":["name"],"parameters":{"name":{"location":"path","pattern":"^projects/[^/]+/notes/[^/]+$","required":true,"type":"string"}},"path":"v1beta1/{+name}","response":{"$ref":"Empty"},"scopes":["https://www.googleapis.com/auth/cloud-platform"]},"get":{"flatPath":"v1beta1/projects/{projectsId}/notes/{notesId}","httpMethod":"GET","id":"containeranalysis.projects.notes.get","parameterOrder":["name"],"parameters":{"name":{"location":"path","pattern":"^projects/[^/]+/notes/[^/]+$","required":true,"type":"string"}},"path":"v1beta1/{+name}","response":{"$ref":"Note"},"scopes":["https://www.googleapis.com/auth/cloud-platform"]},"getIamPolicy":{"flatPath":"v1beta1/projects/{projectsId}/notes/{notesId}:getIamPolicy","httpMethod":"POST","id":"containeranalysis.projects.notes.getIamPolicy","parameterOrder":["resource"],"parameters":{"resource":{"location":"path","pattern":"^projects/[^/]+/notes/[^/]+$","required":true,"type":"string"}},"path":"v1beta1/{+resource}:getIamPolicy","request":{"$ref":"GetIamPolicyRequest"},"response":{"$ref":"Policy"},"scopes":["https://www.googleapis.com/auth/cloud-platform"]},"list":{"flatPath":"v1beta1/projects/{projectsId}/notes","httpMethod":"GET","id":"containeranalysis.projects.notes.list","parameterOrder":["parent"],"parameters":{"filter":{"location":"query","type":"string"},"pageSize":{"format":"int32","location":"query","type":"integer"},"pageToken":{"location":"query","type":"string"},"parent":{"location":"path","pattern":"^projects/[^/]+$","required":true,"type":"string"},"returnPartialSuccess":{"location":"query","type":"boolean"}},"path":"v1beta1/{+parent}/notes","response":{"$ref":"ListNotesResponse"},"scopes":["https://www.googleapis.com/auth/cloud-platform"]},"patch":{"flatPath":"v1beta1/projects/{projectsId}/notes/{notesId}","httpMethod":"PATCH","id":"containeranalysis.projects.notes.patch","parameterOrder":["name"],"parameters":{"name":{"location":"path","pattern":"^projects/[^/]+/notes/[^/]+$","required":true,"type":"string"},"updateMask":{"format":"google-fieldmask","location":"query","type":"string"}},"path":"v1beta1/{+name}","request":{"$ref":"Note"},"response":{"$ref":"Note"},"scopes":["https://www.googleapis.com/auth/cloud-platform"]},"setIamPolicy":{"flatPath":"v1beta1/projects/{projectsId}/notes/{notesId}:setIamPolicy","httpMethod":"POST","id":"containeranalysis.projects.notes.setIamPolicy","parameterOrder":["resource"],"parameters":{"resource":{"location":"path","pattern":"^projects/[^/]+/notes/[^/]+$","required":true,"type":"string"}},"path":"v1beta1/{+resource}:setIamPolicy","request":{"$ref":"SetIamPolicyRequest"},"response":{"$ref":"Policy"},"scopes":["https://www.googleapis.com/auth/cloud-platform"]},"testIamPermissions":{"flatPath":"v1beta1/projects/{projectsId}/notes/{notesId}:testIamPermissions","httpMethod":"POST","id":"containeranalysis.projects.notes.testIamPermissions","parameterOrder":["resource"],"parameters":{"resource":{"location":"path","pattern":"^projects/[^/]+/notes/[^/]+$","required":true,"type":"string"}},"path":"v1beta1/{+resource}:testIamPermissions","request":{"$ref":"TestIamPermissionsRequest"},"response":{"$ref":"TestIamPermissionsResponse"},"scopes":["https://www.googleapis.com/auth/cloud-platform"]}},"resources":{"occurrences":{"methods":{"list":{"flatPath":"v1beta1/projects/{projectsId}/notes/{notesId}/occurrences","httpMethod":"GET","id":"containeranalysis.projects.notes.occurrences.list","parameterOrder":["name"],"parameters":{"filter":{"location":"query","type":"string"},"name":{"location":"path","pattern":"^projects/[^/]+/notes/[^/]+$","required":true,"type":"string"},"pageSize":{"format":"int32","location":"query","type":"integer"},"pageToken":{"location":"query","type":"string"}},"path":"v1beta1/{+name}/occurrences","response":{"$ref":"ListNoteOccurrencesResponse"},"scopes":["https://www.googleapis.com/auth/cloud-platform"]}}}}},"occurrences":{"methods":{"batchCreate":{"flatPath":"v1beta1/projects/{projectsId}/occurrences:batchCreate","httpMethod":"POST","id":"containeranalysis.projects.occurrences.batchCreate","parameterOrder":["parent"],"parameters":{"parent":{"location":"path","pattern":"^projects/[^/]+$","required":true,"type":"string"}},"path":"v1beta1/{+parent}/occurrences:batchCreate","request":{"$ref":"BatchCreateOccurrencesRequest"},"response":{"$ref":"BatchCreateOccurrencesResponse"},"scopes":["https://www.googleapis.com/auth/cloud-platform"]},"create":{"flatPath":"v1beta1/projects/{projectsId}/occurrences","httpMethod":"POST","id":"containeranalysis.projects.occurrences.create","parameterOrder":["parent"],"parameters":{"parent":{"location":"path","pattern":"^projects/[^/]+$","required":true,"type":"string"}},"path":"v1beta1/{+parent}/occurrences","request":{"$ref":"Occurrence"},"response":{"$ref":"Occurrence"},"scopes":["https://www.googleapis.com/auth/cloud-platform"]},"delete":{"flatPath":"v1beta1/projects/{projectsId}/occurrences/{occurrencesId}","httpMethod":"DELETE","id":"containeranalysis.projects.occurrences.delete","parameterOrder":["name"],"parameters":{"name":{"location":"path","pattern":"^projects/[^/]+/occurrences/[^/]+$","required":true,"type":"string"}},"path":"v1beta1/{+name}","response":{"$ref":"Empty"},"scopes":["https://www.googleapis.com/auth/cloud-platform"]},"get":{"flatPath":"v1beta1/projects/{projectsId}/occurrences/{occurrencesId}","httpMethod":"GET","id":"containeranalysis.projects.occurrences.get","parameterOrder":["name"],"parameters":{"name":{"location":"path","pattern":"^projects/[^/]+/occurrences/[^/]+$","required":true,"type":"string"}},"path":"v1beta1/{+name}","response":{"$ref":"Occurrence"},"scopes":["https://www.googleapis.com/auth/cloud-platform"]},"getIamPolicy":{"flatPath":"v1beta1/projects/{projectsId}/occurrences/{occurrencesId}:getIamPolicy","httpMethod":"POST","id":"containeranalysis.projects.occurrences.getIamPolicy","parameterOrder":["resource"],"parameters":{"resource":{"location":"path","pattern":"^projects/[^/]+/occurrences/[^/]+$","required":true,"type":"string"}},"path":"v1beta1/{+resource}:getIamPolicy","request":{"$ref":"GetIamPolicyRequest"},"response":{"$ref":"Policy"},"scopes":["https://www.googleapis.com/auth/cloud-platform"]},"getNotes":{"flatPath":"v1beta1/projects/{projectsId}/occurrences/{occurrencesId}/notes","httpMethod":"GET","id":"containeranalysis.projects.occurrences.getNotes","parameterOrder":["name"],"parameters":{"name":{"location":"path","pattern":"^projects/[^/]+/occurrences/[^/]+$","required":true,"type":"string"}},"path":"v1beta1/{+name}/notes","response":{"$ref":"Note"},"scopes":["https://www.googleapis.com/auth/cloud-platform"]},"getVulnerabilitySummary":{"flatPath":"v1beta1/projects/{projectsId}/occurrences:vulnerabilitySummary","httpMethod":"GET","id":"containeranalysis.projects.occurrences.getVulnerabilitySummary","parameterOrder":["parent"],"parameters":{"filter":{"location":"query","type":"string"},"parent":{"location":"path","pattern":"^projects/[^/]+$","required":true,"type":"string"},"returnPartialSuccess":{"location":"query","type":"boolean"}},"path":"v1beta1/{+parent}/occurrences:vulnerabilitySummary","response":{"$ref":"VulnerabilityOccurrencesSummary"},"scopes":["https://www.googleapis.com/auth/cloud-platform"]},"list":{"flatPath":"v1beta1/projects/{projectsId}/occurrences","httpMethod":"GET","id":"containeranalysis.projects.occurrences.list","parameterOrder":["parent"],"parameters":{"filter":{"location":"query","type":"string"},"pageSize":{"format":"int32","location":"query","type":"integer"},"pageToken":{"location":"query","type":"string"},"parent":{"location":"path","pattern":"^projects/[^/]+$","required":true,"type":"string"},"returnPartialSuccess":{"location":"query","type":"boolean"}},"path":"v1beta1/{+parent}/occurrences","response":{"$ref":"ListOccurrencesResponse"},"scopes":["https://www.googleapis.com/auth/cloud-platform"]},"patch":{"flatPath":"v1beta1/projects/{projectsId}/occurrences/{occurrencesId}","httpMethod":"PATCH","id":"containeranalysis.projects.occurrences.patch","parameterOrder":["name"],"parameters":{"name":{"location":"path","pattern":"^projects/[^/]+/occurrences/[^/]+$","required":true,"type":"string"},"updateMask":{"format":"google-fieldmask","location":"query","type":"string"}},"path":"v1beta1/{+name}","request":{"$ref":"Occurrence"},"response":{"$ref":"Occurrence"},"scopes":["https://www.googleapis.com/auth/cloud-platform"]},"setIamPolicy":{"flatPath":"v1beta1/projects/{projectsId}/occurrences/{occurrencesId}:setIamPolicy","httpMethod":"POST","id":"containeranalysis.projects.occurrences.setIamPolicy","parameterOrder":["resource"],"parameters":{"resource":{"location":"path","pattern":"^projects/[^/]+/occurrences/[^/]+$","required":true,"type":"string"}},"path":"v1beta1/{+resource}:setIamPolicy","request":{"$ref":"SetIamPolicyRequest"},"response":{"$ref":"Policy"},"scopes":["https://www.googleapis.com/auth/cloud-platform"]},"testIamPermissions":{"flatPath":"v1beta1/projects/{projectsId}/occurrences/{occurrencesId}:testIamPermissions","httpMethod":"POST","id":"containeranalysis.projects.occurrences.testIamPermissions","parameterOrder":["resource"],"parameters":{"resource":{"location":"path","pattern":"^projects/[^/]+/occurrences/[^/]+$","required":true,"type":"string"}},"path":"v1beta1/{+resource}:testIamPermissions","request":{"$ref":"TestIamPermissionsRequest"},"response":{"$ref":"TestIamPermissionsResponse"},"scopes":["https://www.googleapis.com/auth/cloud-platform"]}}},"resources":{"methods":{"exportSBOM":{"flatPath":"v1beta1/projects/{projectsId}/resources/{resourcesId}:exportSBOM","httpMethod":"POST","id":"containeranalysis.projects.resources.exportSBOM","parameterOrder":["name"],"parameters":{"name":{"location":"path","pattern":"^projects/[^/]+/resources/.*$","required":true,"type":"string"}},"path":"v1beta1/{+name}:exportSBOM","request":{"$ref":"ExportSBOMRequest"},"response":{"$ref":"ExportSBOMResponse"},"scopes":["https://www.googleapis.com/auth/cloud-platform"]},"generatePackagesSummary":{"flatPath":"v1beta1/projects/{projectsId}/resources/{resourcesId}:generatePackagesSummary","httpMethod":"POST","id":"containeranalysis.projects.resources.generatePackagesSummary","parameterOrder":["name"],"parameters":{"name":{"location":"path","pattern":"^projects/[^/]+/resources/.*$","required":true,"type":"string"}},"path":"v1beta1/{+name}:generatePackagesSummary","request":{"$ref":"GeneratePackagesSummaryRequest"},"response":{"$ref":"PackagesSummaryResponse"},"scopes":["https://www.googleapis.com/auth/cloud-platform"]}}}}}}}
