{"basePath":"","rootUrl":"https://tracing.googleapis.com/","resources":{"projects":{"resources":{"traces":{"methods":{"list":{"parameters":{"filter":{"type":"string","location":"query"},"endTime":{"format":"google-datetime","type":"string","location":"query"},"pageToken":{"location":"query","type":"string"},"startTime":{"format":"google-datetime","type":"string","location":"query"},"pageSize":{"format":"int32","type":"integer","location":"query"},"parent":{"pattern":"^projects/[^/]+$","location":"path","required":true,"type":"string"},"orderBy":{"location":"query","type":"string"}},"scopes":["https://www.googleapis.com/auth/cloud-platform","https://www.googleapis.com/auth/trace.readonly"],"flatPath":"v2/projects/{projectsId}/traces","path":"v2/{+parent}/traces","id":"tracing.projects.traces.list","response":{"$ref":"ListTracesResponse"},"parameterOrder":["parent"],"httpMethod":"GET"},"batchWrite":{"request":{"$ref":"BatchWriteSpansRequest"},"response":{"$ref":"Empty"},"parameterOrder":["name"],"httpMethod":"POST","parameters":{"name":{"required":true,"type":"string","pattern":"^projects/[^/]+$","location":"path"}},"scopes":["https://www.googleapis.com/auth/cloud-platform","https://www.googleapis.com/auth/trace.append"],"flatPath":"v2/projects/{projectsId}/traces:batchWrite","path":"v2/{+name}/traces:batchWrite","id":"tracing.projects.traces.batchWrite"},"listSpans":{"response":{"$ref":"ListSpansResponse"},"parameterOrder":["parent"],"httpMethod":"GET","scopes":["https://www.googleapis.com/auth/cloud-platform","https://www.googleapis.com/auth/trace.readonly"],"parameters":{"parent":{"pattern":"^projects/[^/]+/traces/[^/]+$","location":"path","required":true,"type":"string"},"pageToken":{"location":"query","type":"string"}},"flatPath":"v2/projects/{projectsId}/traces/{tracesId}:listSpans","path":"v2/{+parent}:listSpans","id":"tracing.projects.traces.listSpans"}},"resources":{"spans":{"methods":{"create":{"flatPath":"v2/projects/{projectsId}/traces/{tracesId}/spans/{spansId}","path":"v2/{+name}","id":"tracing.projects.traces.spans.create","request":{"$ref":"Span"},"response":{"$ref":"Span"},"parameterOrder":["name"],"httpMethod":"PUT","parameters":{"name":{"location":"path","required":true,"type":"string","pattern":"^projects/[^/]+/traces/[^/]+/spans/[^/]+$"}},"scopes":["https://www.googleapis.com/auth/cloud-platform","https://www.googleapis.com/auth/trace.append"]}}}}}}}}}
