{"basePath":"","rootUrl":"https://accessapproval.googleapis.com/","resources":{"folders":{"methods":{"deleteAccessApprovalSettings":{"flatPath":"v1beta1/folders/{foldersId}/accessApprovalSettings","httpMethod":"DELETE","id":"accessapproval.folders.deleteAccessApprovalSettings","parameterOrder":["name"],"parameters":{"name":{"location":"path","pattern":"^folders/[^/]+/accessApprovalSettings$","required":true,"type":"string"}},"path":"v1beta1/{+name}","response":{"$ref":"Empty"},"scopes":["https://www.googleapis.com/auth/cloud-platform"]},"getAccessApprovalSettings":{"flatPath":"v1beta1/folders/{foldersId}/accessApprovalSettings","httpMethod":"GET","id":"accessapproval.folders.getAccessApprovalSettings","parameterOrder":["name"],"parameters":{"name":{"location":"path","pattern":"^folders/[^/]+/accessApprovalSettings$","required":true,"type":"string"}},"path":"v1beta1/{+name}","response":{"$ref":"AccessApprovalSettings"},"scopes":["https://www.googleapis.com/auth/cloud-platform"]},"updateAccessApprovalSettings":{"flatPath":"v1beta1/folders/{foldersId}/accessApprovalSettings","httpMethod":"PATCH","id":"accessapproval.folders.updateAccessApprovalSettings","parameterOrder":["name"],"parameters":{"name":{"location":"path","pattern":"^folders/[^/]+/accessApprovalSettings$","required":true,"type":"string"},"updateMask":{"format":"google-fieldmask","location":"query","type":"string"}},"path":"v1beta1/{+name}","request":{"$ref":"AccessApprovalSettings"},"response":{"$ref":"AccessApprovalSettings"},"scopes":["https://www.googleapis.com/auth/cloud-platform"]}},"resources":{"approvalRequests":{"methods":{"approve":{"flatPath":"v1beta1/folders/{foldersId}/approvalRequests/{approvalRequestsId}:approve","httpMethod":"POST","id":"accessapproval.folders.approvalRequests.approve","parameterOrder":["name"],"parameters":{"name":{"location":"path","pattern":"^folders/[^/]+/approvalRequests/[^/]+$","required":true,"type":"string"}},"path":"v1beta1/{+name}:approve","request":{"$ref":"ApproveApprovalRequestMessage"},"response":{"$ref":"ApprovalRequest"},"scopes":["https://www.googleapis.com/auth/cloud-platform"]},"dismiss":{"flatPath":"v1beta1/folders/{foldersId}/approvalRequests/{approvalRequestsId}:dismiss","httpMethod":"POST","id":"accessapproval.folders.approvalRequests.dismiss","parameterOrder":["name"],"parameters":{"name":{"location":"path","pattern":"^folders/[^/]+/approvalRequests/[^/]+$","required":true,"type":"string"}},"path":"v1beta1/{+name}:dismiss","request":{"$ref":"DismissApprovalRequestMessage"},"response":{"$ref":"ApprovalRequest"},"scopes":["https://www.googleapis.com/auth/cloud-platform"]},"get":{"flatPath":"v1beta1/folders/{foldersId}/approvalRequests/{approvalRequestsId}","httpMethod":"GET","id":"accessapproval.folders.approvalRequests.get","parameterOrder":["name"],"parameters":{"name":{"location":"path","pattern":"^folders/[^/]+/approvalRequests/[^/]+$","required":true,"type":"string"}},"path":"v1beta1/{+name}","response":{"$ref":"ApprovalRequest"},"scopes":["https://www.googleapis.com/auth/cloud-platform"]},"list":{"flatPath":"v1beta1/folders/{foldersId}/approvalRequests","httpMethod":"GET","id":"accessapproval.folders.approvalRequests.list","parameterOrder":["parent"],"parameters":{"filter":{"location":"query","type":"string"},"pageSize":{"format":"int32","location":"query","type":"integer"},"pageToken":{"location":"query","type":"string"},"parent":{"location":"path","pattern":"^folders/[^/]+$","required":true,"type":"string"}},"path":"v1beta1/{+parent}/approvalRequests","response":{"$ref":"ListApprovalRequestsResponse"},"scopes":["https://www.googleapis.com/auth/cloud-platform"]}}}}},"organizations":{"methods":{"deleteAccessApprovalSettings":{"flatPath":"v1beta1/organizations/{organizationsId}/accessApprovalSettings","httpMethod":"DELETE","id":"accessapproval.organizations.deleteAccessApprovalSettings","parameterOrder":["name"],"parameters":{"name":{"location":"path","pattern":"^organizations/[^/]+/accessApprovalSettings$","required":true,"type":"string"}},"path":"v1beta1/{+name}","response":{"$ref":"Empty"},"scopes":["https://www.googleapis.com/auth/cloud-platform"]},"getAccessApprovalSettings":{"flatPath":"v1beta1/organizations/{organizationsId}/accessApprovalSettings","httpMethod":"GET","id":"accessapproval.organizations.getAccessApprovalSettings","parameterOrder":["name"],"parameters":{"name":{"location":"path","pattern":"^organizations/[^/]+/accessApprovalSettings$","required":true,"type":"string"}},"path":"v1beta1/{+name}","response":{"$ref":"AccessApprovalSettings"},"scopes":["https://www.googleapis.com/auth/cloud-platform"]},"updateAccessApprovalSettings":{"flatPath":"v1beta1/organizations/{organizationsId}/accessApprovalSettings","httpMethod":"PATCH","id":"accessapproval.organizations.updateAccessApprovalSettings","parameterOrder":["name"],"parameters":{"name":{"location":"path","pattern":"^organizations/[^/]+/accessApprovalSettings$","required":true,"type":"string"},"updateMask":{"format":"google-fieldmask","location":"query","type":"string"}},"path":"v1beta1/{+name}","request":{"$ref":"AccessApprovalSettings"},"response":{"$ref":"AccessApprovalSettings"},"scopes":["https://www.googleapis.com/auth/cloud-platform"]}},"resources":{"approvalRequests":{"methods":{"approve":{"flatPath":"v1beta1/organizations/{organizationsId}/approvalRequests/{approvalRequestsId}:approve","httpMethod":"POST","id":"accessapproval.organizations.approvalRequests.approve","parameterOrder":["name"],"parameters":{"name":{"location":"path","pattern":"^organizations/[^/]+/approvalRequests/[^/]+$","required":true,"type":"string"}},"path":"v1beta1/{+name}:approve","request":{"$ref":"ApproveApprovalRequestMessage"},"response":{"$ref":"ApprovalRequest"},"scopes":["https://www.googleapis.com/auth/cloud-platform"]},"dismiss":{"flatPath":"v1beta1/organizations/{organizationsId}/approvalRequests/{approvalRequestsId}:dismiss","httpMethod":"POST","id":"accessapproval.organizations.approvalRequests.dismiss","parameterOrder":["name"],"parameters":{"name":{"location":"path","pattern":"^organizations/[^/]+/approvalRequests/[^/]+$","required":true,"type":"string"}},"path":"v1beta1/{+name}:dismiss","request":{"$ref":"DismissApprovalRequestMessage"},"response":{"$ref":"ApprovalRequest"},"scopes":["https://www.googleapis.com/auth/cloud-platform"]},"get":{"flatPath":"v1beta1/organizations/{organizationsId}/approvalRequests/{approvalRequestsId}","httpMethod":"GET","id":"accessapproval.organizations.approvalRequests.get","parameterOrder":["name"],"parameters":{"name":{"location":"path","pattern":"^organizations/[^/]+/approvalRequests/[^/]+$","required":true,"type":"string"}},"path":"v1beta1/{+name}","response":{"$ref":"ApprovalRequest"},"scopes":["https://www.googleapis.com/auth/cloud-platform"]},"list":{"flatPath":"v1beta1/organizations/{organizationsId}/approvalRequests","httpMethod":"GET","id":"accessapproval.organizations.approvalRequests.list","parameterOrder":["parent"],"parameters":{"filter":{"location":"query","type":"string"},"pageSize":{"format":"int32","location":"query","type":"integer"},"pageToken":{"location":"query","type":"string"},"parent":{"location":"path","pattern":"^organizations/[^/]+$","required":true,"type":"string"}},"path":"v1beta1/{+parent}/approvalRequests","response":{"$ref":"ListApprovalRequestsResponse"},"scopes":["https://www.googleapis.com/auth/cloud-platform"]}}}}},"projects":{"methods":{"deleteAccessApprovalSettings":{"flatPath":"v1beta1/projects/{projectsId}/accessApprovalSettings","httpMethod":"DELETE","id":"accessapproval.projects.deleteAccessApprovalSettings","parameterOrder":["name"],"parameters":{"name":{"location":"path","pattern":"^projects/[^/]+/accessApprovalSettings$","required":true,"type":"string"}},"path":"v1beta1/{+name}","response":{"$ref":"Empty"},"scopes":["https://www.googleapis.com/auth/cloud-platform"]},"getAccessApprovalSettings":{"flatPath":"v1beta1/projects/{projectsId}/accessApprovalSettings","httpMethod":"GET","id":"accessapproval.projects.getAccessApprovalSettings","parameterOrder":["name"],"parameters":{"name":{"location":"path","pattern":"^projects/[^/]+/accessApprovalSettings$","required":true,"type":"string"}},"path":"v1beta1/{+name}","response":{"$ref":"AccessApprovalSettings"},"scopes":["https://www.googleapis.com/auth/cloud-platform"]},"updateAccessApprovalSettings":{"flatPath":"v1beta1/projects/{projectsId}/accessApprovalSettings","httpMethod":"PATCH","id":"accessapproval.projects.updateAccessApprovalSettings","parameterOrder":["name"],"parameters":{"name":{"location":"path","pattern":"^projects/[^/]+/accessApprovalSettings$","required":true,"type":"string"},"updateMask":{"format":"google-fieldmask","location":"query","type":"string"}},"path":"v1beta1/{+name}","request":{"$ref":"AccessApprovalSettings"},"response":{"$ref":"AccessApprovalSettings"},"scopes":["https://www.googleapis.com/auth/cloud-platform"]}},"resources":{"approvalRequests":{"methods":{"approve":{"flatPath":"v1beta1/projects/{projectsId}/approvalRequests/{approvalRequestsId}:approve","httpMethod":"POST","id":"accessapproval.projects.approvalRequests.approve","parameterOrder":["name"],"parameters":{"name":{"location":"path","pattern":"^projects/[^/]+/approvalRequests/[^/]+$","required":true,"type":"string"}},"path":"v1beta1/{+name}:approve","request":{"$ref":"ApproveApprovalRequestMessage"},"response":{"$ref":"ApprovalRequest"},"scopes":["https://www.googleapis.com/auth/cloud-platform"]},"dismiss":{"flatPath":"v1beta1/projects/{projectsId}/approvalRequests/{approvalRequestsId}:dismiss","httpMethod":"POST","id":"accessapproval.projects.approvalRequests.dismiss","parameterOrder":["name"],"parameters":{"name":{"location":"path","pattern":"^projects/[^/]+/approvalRequests/[^/]+$","required":true,"type":"string"}},"path":"v1beta1/{+name}:dismiss","request":{"$ref":"DismissApprovalRequestMessage"},"response":{"$ref":"ApprovalRequest"},"scopes":["https://www.googleapis.com/auth/cloud-platform"]},"get":{"flatPath":"v1beta1/projects/{projectsId}/approvalRequests/{approvalRequestsId}","httpMethod":"GET","id":"accessapproval.projects.approvalRequests.get","parameterOrder":["name"],"parameters":{"name":{"location":"path","pattern":"^projects/[^/]+/approvalRequests/[^/]+$","required":true,"type":"string"}},"path":"v1beta1/{+name}","response":{"$ref":"ApprovalRequest"},"scopes":["https://www.googleapis.com/auth/cloud-platform"]},"list":{"flatPath":"v1beta1/projects/{projectsId}/approvalRequests","httpMethod":"GET","id":"accessapproval.projects.approvalRequests.list","parameterOrder":["parent"],"parameters":{"filter":{"location":"query","type":"string"},"pageSize":{"format":"int32","location":"query","type":"integer"},"pageToken":{"location":"query","type":"string"},"parent":{"location":"path","pattern":"^projects/[^/]+$","required":true,"type":"string"}},"path":"v1beta1/{+parent}/approvalRequests","response":{"$ref":"ListApprovalRequestsResponse"},"scopes":["https://www.googleapis.com/auth/cloud-platform"]}}}}}}}
